{
  "App.Title": "Print Maestro",
  "Button.AddFiles": "Добавить файлы",
  "Button.AddFolder": "Добавить папку",
  "Button.StartPrint": "Начать печать",
  "Button.Pause": "Пауза",
  "Button.ResumePrint": "Продолжить",
  "Button.CancelPrint": "Отменить печать",
  "Button.ClearCompleted": "Очистить завершённые",
  "Button.Remove": "Удалить",
  "Button.Close": "Закрыть",
  "Button.Cancel": "Отмена",
  "Menu.Settings": "Настройки",
  "Menu.History": "История печати",
  "Window.Minimize": "Свернуть",
  "Window.Maximize": "Развернуть",
  "Window.Restore": "Восстановить",
  "Window.Close": "Закрыть",
  "Menu.PauseJob": "Приостановить",
  "Menu.ResumeJob": "Возобновить",
  "Menu.RetryJob": "Повторить",
  "Menu.CancelJob": "Отменить",
  "Settings.AppTitle": "Настройки",
  "Queue.Title": "Очередь печати",
  "Settings.Title": "Настройки печати",
  "Settings.Printer": "Принтер",
  "Settings.PaperFormat": "Формат",
  "Settings.Orientation": "Ориентация",
  "Settings.Copies": "Копии",
  "Settings.Duplex": "Двусторонняя печать",
  "Settings.InsertBlankPageAfter": "Добавить пустую страницу",
  "Settings.Language": "Язык",
  "Settings.PdfRenderDpi": "Качество печати PDF (DPI)",
  "Settings.PdfRenderDpiHint": "Диапазон: 150-400",
  "Settings.Tab.General": "Общие",
  "Settings.Tab.Profiles": "Профили",
  "Settings.Tab.About": "О программе",
  "PaperFormat.A4": "A4",
  "PaperFormat.A3": "A3",
  "Orientation.Auto": "Авто",
  "Orientation.Portrait": "Книжная",
  "Orientation.Landscape": "Альбомная",
  "Status.Ready": "Готов к работе",
  "Status.AddDocumentsHint": "Добавьте документы в очередь",
  "Status.PrintStarted": "Печать запущена",
  "Status.PrintCompleted": "Очередь печати завершена",
  "Status.PrintStopped": "Печать остановлена",
  "Status.PrintPaused": "Печать приостановлена",
  "Status.CompletedCleared": "Завершённые задания удалены",
  "Status.FilesAdded": "Добавлено файлов: {0}",
  "Status.UpdateAvailable": "Доступно обновление v{0}",
  "StatusBar.Total": "Всего:",
  "StatusBar.Completed": "Готово:",
  "StatusBar.Errors": "Ошибки:",
  "JobStatus.Pending": "В очереди",
  "JobStatus.Preparing": "Подготовка",
  "JobStatus.Dispatching": "Отправка",
  "JobStatus.Spooled": "В spooler",
  "JobStatus.Printing": "Печать",
  "JobStatus.Completed": "Завершено",
  "JobStatus.Failed": "Ошибка",
  "JobStatus.Paused": "Пауза",
  "JobStatus.Canceled": "Отменено",
  "JobStatus.RetryWaiting": "Ожидание повтора",
  "Language.en": "English",
  "Language.ru": "Русский",
  "Dialog.Shutdown.Title": "Выход из Print Maestro",
  "Dialog.Shutdown.Message": "Есть активные задания. Завершить работу?",
  "Dialog.AlreadyRunning.Title": "Print Maestro",
  "Dialog.AlreadyRunning.Message": "Print Maestro уже запущен.",
  "Dialog.Update.Title": "Доступно обновление",
  "Dialog.Update.Message": "Установить Print Maestro v{0}? Приложение будет закрыто для установки.",
  "Toast.PrintStarted": "Очередь печати запущена",
  "Toast.PrintPaused": "Очередь печати приостановлена",
  "Toast.PrintCanceled": "Печать отменена",
  "Toast.PrintResumed": "Очередь печати возобновлена",
  "Toast.JobRemoved": "Задание удалено из очереди",
  "Toast.JobPaused": "Задание приостановлено",
  "Toast.JobResumed": "Задание возобновлено",
  "Toast.JobRetry": "Задание поставлено на повтор",
  "Toast.JobCanceled": "Задание отменено",
  "Toast.QueueReordered": "Порядок очереди обновлён",
  "Toast.NoSupportedFiles": "Поддерживаемые файлы не найдены",
  "Toast.FilesSkipped": "Пропущено неподдерживаемых файлов: {0}",
  "History.Title": "История печати",
  "History.Refresh": "Обновить",
  "History.Clear": "Очистить",
  "History.Result.Success": "Успех",
  "History.Result.Failed": "Ошибка",
  "History.Column.File": "Файл",
  "History.Column.Printer": "Принтер",
  "History.Column.Started": "Начало",
  "History.Column.Result": "Результат",
  "History.Column.Copies": "Копии",
  "History.Column.Error": "Ошибка",
  "Profiles.Select": "Профиль",
  "Profiles.SaveCurrent": "Сохранить текущие настройки…",
  "Profiles.SaveTitle": "Сохранить профиль",
  "Profiles.SavePrompt": "Введите имя профиля:",
  "Profiles.Saved": "Профиль «{0}» сохранён",
  "Profiles.Delete": "Удалить профиль",
  "Profiles.ManageHint": "Сохраните текущие настройки печати как профиль. Здесь же можно удалить ненужные профили.",
  "About.Title": "Print Maestro",
  "About.Version": "Версия ",
  "About.Description": "Пакетная последовательная печать документов для Windows.",
  "About.OpenLicenses": "Сторонние лицензии"
}
